LICENSE
MANIFEST.in
README.rst
requirements.txt
setup.py
smoomapy/__init__.py
smoomapy/core.py
smoomapy/helpers_classif.py
smoomapy.egg-info/PKG-INFO
smoomapy.egg-info/SOURCES.txt
smoomapy.egg-info/dependency_links.txt
smoomapy.egg-info/requires.txt
smoomapy.egg-info/top_level.txt