Metadata-Version: 1.1
Name: smoomapy
Version: 0.1.4
Summary: Brings smoothed maps through python
Home-page: http://github.com/mthh/smoomapy
Author: Matthieu Viry
Author-email: matthieu.viry@ums-riate.fr
License: MIT
Platform: UNKNOWN
Classifier: Programming Language :: Python
Classifier: Development Status :: 2 - Pre-Alpha
Classifier: License :: OSI Approved :: MIT License
Classifier: Operating System :: OS Independent
Classifier: Programming Language :: Python :: 2.7
Classifier: Programming Language :: Python :: 3.4
Classifier: Programming Language :: Python :: 3.5
Classifier: Topic :: Scientific/Engineering
